{
  "one_liner": "극소형주 바이오텍 회사로 높은 변동성과 리스크가 존재",
  "strengths": [
    "현금 잔고가 충분하여 단기 자금 부족 리스크가 낮다.",
    "다양한 임상 파이프라인을 보유하고 있어 미래 성장 가능성이 있다.",
    "NUC-7738과 같은 주요 임상 후보물질의 진행이 주가에 긍정적 영향을 줄 수 있다."
  ],
  "risks": [
    "극소형주로 유동성 부족과 높은 변동성이 존재하여 투자 위험이 크다.",
    "임상 중단 이력이 있어 파이프라인의 집중 리스크가 있다.",
    "Phase 3 바이너리 이벤트 결과에 따라 주가가 급등 또는 급락할 수 있다."
  ],
  "key_catalysts": [
    "NUC-7738의 임상 결과",
    "Phase 3 바이너리 이벤트 결과"
  ],
  "investment_view": "NuCana plc는 높은 변동성과 리스크를 가진 극소형주 바이오텍 회사입니다. 다양한 임상 파이프라인과 충분한 현금 잔고는 장기적인 성장 가능성을 제공하지만, 임상 중단 이력과 유동성 부족은 주요 우려 요소입니다. 따라서 이 회사는 높은 리스크를 감수할 수 있는 투자자에게 적합하며, 주가의 급등 또는 급락 가능성을 고려하여 투자 quyết策을 내릴 필요가 있습니다.",
  "disclaimer": "본 분석은 특정 투자 의견을 제공하기 위한 것이 아니며, 투자 결정에 참고할 수 있는 정보를 제공하는 것을 목적으로 합니다.",
  "updated_at": "2026-04-24T01:45:33.855996",
  "model": "groq/llama-3.3-70b-versatile"
}